CHANGES.txt
LICENSE.txt
README.txt
bootstrap.py
buildout.cfg
setup.py
js/__init__.py
js.jquery_spin.egg-info/PKG-INFO
js.jquery_spin.egg-info/SOURCES.txt
js.jquery_spin.egg-info/dependency_links.txt
js.jquery_spin.egg-info/entry_points.txt
js.jquery_spin.egg-info/namespace_packages.txt
js.jquery_spin.egg-info/not-zip-safe
js.jquery_spin.egg-info/requires.txt
js.jquery_spin.egg-info/top_level.txt
js/jquery_spin/__init__.py
js/jquery_spin/test_jquery.spin.txt
js/jquery_spin/resources/jquery.spin.js