Metadata-Version: 1.0
Name: js.jquery-spin
Version: 1.0
Summary: Fanstatic packaging of jquery.spin
Home-page: UNKNOWN
Author: Fanstatic Developers
Author-email: fanstatic@googlegroups.com
License: BSD
Platform: UNKNOWN
